simpleconjoint/__init__.py
simpleconjoint/cbc.py
simpleconjoint/constants.py
simpleconjoint-0.0.1.dist-info/LICENSE
simpleconjoint-0.0.1.dist-info/METADATA
simpleconjoint-0.0.1.dist-info/WHEEL
simpleconjoint-0.0.1.dist-info/top_level.txt
simpleconjoint-0.0.1.dist-info/RECORD
